{"cameraMode":{"drawMode":0,"name":"Shaded","section":"Shading Mode"},"sceneLighting":false,"audioPlay":false,"sceneViewState":{"showFog":true,"showMaterialUpdate":false,"showSkybox":false,"showFlares":true,"showImageEffects":true,"showParticleSystems":true},"in2DMode":false,"pivot":{"x":-2.4222404956817629,"y":1.3987030982971192,"z":-0.7052316665649414},"rotation":{"x":0.19132304191589356,"y":0.7059673070907593,"z":-0.2079818695783615,"w":0.649422287940979},"size":2.1342480182647707,"orthographic":false}